Metadata-Version: 2.1
Name: WolframAlpha.py
Version: 1.1.5
Summary: A WolframAlpha API Wrapper for Python.
Home-page: https://github.com/Nemika-Haj/WolframAlpha.py
Author: Nemika
Author-email: nemika@bytestobits.dev
License: MIT
Keywords: wolfram,wolframalpha,wolfram.py,wolframalpha.py,wrapper
Platform: UNKNOWN
Classifier: Intended Audience :: Developers
Classifier: Topic :: Software Development :: Build Tools
Classifier: License :: OSI Approved :: MIT License
Classifier: Programming Language :: Python :: 3
Classifier: Programming Language :: Python :: 3.4
Classifier: Programming Language :: Python :: 3.5
Classifier: Programming Language :: Python :: 3.6
Classifier: Programming Language :: Python :: 3.7
Classifier: Programming Language :: Python :: 3.8
Classifier: Programming Language :: Python :: 3.9
